__init__.py
lic.py
license_gen-1.1.0.dist-info/LICENSE
license_gen-1.1.0.dist-info/METADATA
license_gen-1.1.0.dist-info/WHEEL
license_gen-1.1.0.dist-info/entry_points.txt
license_gen-1.1.0.dist-info/top_level.txt
license_gen-1.1.0.dist-info/RECORD
